simpleFileCache/__init__.py
simpleFileCache/cacher.py
simpleFileCache/index.py
simpleFileCache/logger.py
simpleFileCache/meta.py
simpleFileCache/utils/crypt.py
simpleFileCache/utils/git.py
simpleFileCache/utils/hashing.py
simpleFileCache/utils/json.py
simpleFileCache24-1.1.0.dist-info/LICENSE
simpleFileCache24-1.1.0.dist-info/METADATA
simpleFileCache24-1.1.0.dist-info/WHEEL
simpleFileCache24-1.1.0.dist-info/top_level.txt
simpleFileCache24-1.1.0.dist-info/RECORD
