Metadata-Version: 2.1
Name: simpleFileCache24
Version: 1.1.0
Author: zackaryW
License-File: LICENSE
Requires-Dist: cryptography
Requires-Dist: keyring
Requires-Dist: requests
Requires-Dist: sioDict >=0.3.2
